README.txt
setup.py
genshimacro/__init__.py
trac_GenshiMacro.egg-info/PKG-INFO
trac_GenshiMacro.egg-info/SOURCES.txt
trac_GenshiMacro.egg-info/dependency_links.txt
trac_GenshiMacro.egg-info/entry_points.txt
trac_GenshiMacro.egg-info/not-zip-safe
trac_GenshiMacro.egg-info/top_level.txt