Metadata-Version: 1.0
Name: trac-GenshiMacro
Version: 0.1
Summary: Write Genshi templates in Trac wiki pages
Home-page: http://trac-hacks.org/wiki/GenshiMacro
Author: Ethan Jucovy
Author-email: ejucovy@gmail.com
License: BSD
Keywords: trac plugin
Platform: UNKNOWN
